{
  "lastname": "MENEGHETTI",
  "firstname": "Damien",
  "anonyme_name": "Profil 1",
  "profil_path": "default.webp",
  "profession": "Développeur Fullstack",
  "location": "11 Rue Albert 1er - 98800 Nouméa",
  "email": "damien.meneghetti@deveo.nc",
  "phoneWithIndicator": "+687959112",
  "phone": "+687 95 91 12",
  "skills": [
    {
      "category": "MÉTHODOLOGIES",
      "subCategories": [
        {
          "subCategory": "Approche",
          "description": "UML, AGILE SCRUM, TDD, DDD"
        }
      ]
    },
    {
      "category": "LANGAGES",
      "subCategories": [
        {
          "subCategory": "Langages/Scripts Backend",
          "description": "Java/JEE, Python, C, C++, Go, Kotlin, Swift, Node.js, Rust"
        },
        {
          "subCategory": "Langages/Script Web",
          "description": "HTML5, CSS3, Javascript, Typescript, JSP, PHP"
        },
        {
          "subCategory": "Langages Database",
          "description": "SQL, PL/SQL"
        }
      ]
    },
    {
      "category": "FRAMEWORKS ET BIBLIOTHÈQUES",
      "subCategories": [
        {
          "subCategory": "Frameworks Backend",
          "description": "Spring Boot, Spring Batch, Spring MVC, Grails, Quarkus, Hibernate, JPA, Struts"
        },
        {
          "subCategory": "Frameworks Frontend",
          "description": "Angular, React, Vue.js, ExtJS, NextJS, GWT, Wicket"
        },
        {
          "subCategory": "Frameworks UI/UX",
          "description": "Material Design, Bootstrap, Tailwind CSS, PrimeNG, ShadCN, Ant, Radix"
        }
      ]
    },
    {
      "category": "TECHNOLOGIES ET OUTILS",
      "subCategories": [
        {
          "subCategory": "DevOps",
          "description": "Docker, Kubernetes, Prometheus, Grafana, Github Actions, CircleCI, Jenkins, SonarQube, Hudson"
        },
        {
          "subCategory": "Cloud",
          "description": "AWS, Azure, Google Cloud, Cloudflare"
        },
        {
          "subCategory": "Data Engineering",
          "description": "Apache Kafka, Apache Flink, Hadoop, Spark, RedPanda Console, Airflow"
        },
        {
          "subCategory": "Gestion des APIs",
          "description": "Postman, Swagger, Apigee, OpenAPI, Bruno"
        },
        {
          "subCategory": "Serveurs d'Application",
          "description": "TomCat, JBoss, GlassFish, Weblogic Server, Jonas, Nginx"
        },
        {
          "subCategory": "IDE",
          "description": "IntelliJ, Eclipse, NetBeans, VS Code, Weblogic Workshop"
        },
        {
          "subCategory": "Gestion de config",
          "description": "Git, CVS, SVN, ClearCase"
        }
      ]
    },
    {
      "category": "BASES DE DONNEES",
      "subCategories": [
        {
          "subCategory": "SGBD et NoSQL",
          "description": "Oracle 10g, MySQL, PostgreSQL, Elasticsearch, Couchbase, Amazon Redshift, MongoDB, DynamoDB"
        },
        {
          "subCategory": "Outils",
          "description": "SQL Developer, SQLyog, Toad, DBeaver, Flyway, Liquibase"
        }
      ]
    },
    {
      "category": "TESTS ET QUALITÉ",
      "subCategories": [
        {
          "subCategory": "Tests automatisés",
          "description": "JUnit, Jest, Karma, Jasmine, JMeter, Gatling, Selenium, Cypress, Quality Center, TestNG"
        },
        {
          "subCategory": "Qualité",
          "description": "SonarQube, ESLint, Prettier, Checkstyle"
        }
      ]
    },
    {
      "category": "INTÉGRATION ET MIDDLEWARE",
      "subCategories": [
        {
          "subCategory": "EAI & B2BI",
          "description": "BEA Weblogic integration 8.1 SP5"
        }
      ]
    }
  ],
  "languages": [
    {
      "description": "Français",
      "level": 5
    },
    {
      "description": "Anglais",
      "level": 5
    },
    {
      "description": "Allemand",
      "level": 3
    }
  ],
  "experiences": [
    {
      "title": "Développeur Fullstack - DEVEO",
      "company": "OPT | Service bancaire - Nouméa",
      "year": "Janvier 2024 - Maintenant",
      "description": "Projet Mana",
      "environments": [
        {
          "iconPack": "fab",
          "icon": "angular",
          "description": "ANGULAR 18, JSON, REST"
        },
        {
          "iconPack": "fas",
          "icon": "leaf",
          "description": "SPRING BOOT 3, SPRING BATCH"
        },
        {
          "iconPack": "fab",
          "icon": "github",
          "description": "INTELIJ, GIT"
        },
        {
          "iconPack": "fas",
          "icon": "tasks",
          "description": "AGILE SCRUM, JIRA"
        }
      ],
      "tasks": [
        "Cubilia a hac purus duis lacinia quis.",
        "Est sapien nisi tristique blandit justo integer vestibulum sit felis eu.",
        "Ultrices magnis nostra justo mi convallis aliquam.",
        "Laoreet curabitur massa litora blandit odio vulputate dui nostra molestie luctus."
      ]
    },
    {
      "title": "Team leader / Developpeur Fullstack - DEVEO",
      "company": "DITTT | Service blabla - Nouméa",
      "year": "Juin 2022 - Mars 2023",
      "description": "Projet PICO2",
      "environments": [
        {
          "iconPack": "fab",
          "icon": "angular",
          "description": "ANGULAR 18, JSON, REST"
        },
        {
          "iconPack": "fas",
          "icon": "leaf",
          "description": "SPRING BOOT 3, SPRING BATCH"
        },
        {
          "iconPack": "fab",
          "icon": "github",
          "description": "INTELIJ, GIT"
        },
        {
          "iconPack": "fas",
          "icon": "tasks",
          "description": "AGILE SCRUM, JIRA"
        }
      ],
      "tasks": [
        "Projet de refonte de l'application de gestion des permis de conduire",
        "Mise en place de l'architecture logiciel et encadrement de l'équipe de développement",
        "Développement de nouvelles fonctionnalités dans l'application de gestion des Permis de conduire de la DITTT",
        "Etude, conception et développement de l'application dans une équipe de 4/5 développeurs et 1 Product Owner"
      ]
    },
    {
      "title": "Développeur Fullstack - DEVEO",
      "company": "OPT | Service Relation Client - Nouméa",
      "year": "Novembre 2021 - Juin 2022",
      "description": "Projet KWC",
      "environments": [
        {
          "iconPack": "fab",
          "icon": "angular",
          "description": "ANGULAR 18, JSON, REST"
        },
        {
          "iconPack": "fas",
          "icon": "leaf",
          "description": "SPRING BOOT 3, SPRING BATCH"
        },
        {
          "iconPack": "fab",
          "icon": "github",
          "description": "INTELIJ, GIT"
        },
        {
          "iconPack": "fas",
          "icon": "tasks",
          "description": "AGILE SCRUM, JIRA"
        }
      ],
      "tasks": [
        "Cubilia a hac purus duis lacinia quis.",
        "Est sapien nisi tristique blandit justo integer vestibulum sit felis eu.",
        "Ultrices magnis nostra justo mi convallis aliquam.",
        "Laoreet curabitur massa litora blandit odio vulputate dui nostra molestie luctus."
      ]
    },
    {
      "title": "Scrum master / Développeur Fullstack - VIRTUAL-EXPO",
      "company": "VIRTUAL-EXPO | Service dqzd - France",
      "year": "Novembre 2018 - Juin 2021",
      "description": "Migration technique d'une marketplace B2B sujette à de fortes contraintes SEO & performances, amélioration du côté ‘responsive’ du parc applicatif.",
      "environments": [
        {
          "iconPack": "fab",
          "icon": "angular",
          "description": "REACT, HTML5, CSS3, WEBVITALS, LIGHTOUSE"
        },
        {
          "iconPack": "fas",
          "icon": "leaf",
          "description": "JAVA, JPA, MYSQL, JUNIT"
        },
        {
          "iconPack": "fab",
          "icon": "github",
          "description": "VISUAL STUDIO CODE, GIT, JENKINS"
        },
        {
          "iconPack": "fas",
          "icon": "tasks",
          "description": "AGILE SCRUM, JIRA"
        }
      ],
      "tasks": [
        "Migration de JSP vers React JS d’une application Web",
        "Analyse et optimisation des performances et du référencement",
        "Amélioration du comportement mobile des back-offices"
      ]
    },
    {
      "title": "Team leader / Développeur Fullstack - SMARTTRADE",
      "company": "SMARTTRADE | Service dqzd - France",
      "year": "Juin 2016 - Novembre 2018",
      "description": "Refonte technique et ergonomique d'une application d’administration permettant de configurer et de monitorer les activités de trading",
      "environments": [
        {
          "iconPack": "fab",
          "icon": "angular",
          "description": "JAVASCRIPT, HTML5, CSS3"
        },
        {
          "iconPack": "fas",
          "icon": "leaf",
          "description": "JAVA, GWT, JAVERS, SPRING BOOT, SPRING BATCH, SPRING DATA, JPA, MYSQL, JUNIT"
        },
        {
          "iconPack": "fab",
          "icon": "github",
          "description": "ECLIPSE, GIT, JENKINS, BAMBOO"
        },
        {
          "iconPack": "fas",
          "icon": "tasks",
          "description": "AGILE SCRUM"
        }
      ],
      "tasks": [
        "Définition de l’architecture logicielle du projet",
        "Conception et développement d’un framework de validation et d’audit",
        "Remaniement de la UI/UX centré autour du besoin fonctionnel",
        "Gestion d’une équipe"
      ]
    },
    {
      "title": "Développeur Fullstack - TAPVALUE / INSTORE·DIGITAL",
      "company": "TAPVALUE / INSTORE·DIGITAL | Service dqzd - France",
      "year": "Juin 2014 - Novembre 2016",
      "description": "Conception et développement d'une plateforme permettant d’analyser et de comprendre le parcours client en magasin et sur le web, et d’interagir avec ce dernier afin de monétiser l’information",
      "environments": [
        {
          "iconPack": "fab",
          "icon": "angular",
          "description": "JAVASCRIPT, GWT, HTML5, CSS3, BOOTSTRAP"
        },
        {
          "iconPack": "fas",
          "icon": "leaf",
          "description": "JAVA, JPA, TOMCAT, SPRING MVC, POSTGRESQL, COUCHBASE, ELASTICSEARCH, JUNIT, AMAZON REDSHIFT"
        },
        {
          "iconPack": "fab",
          "icon": "github",
          "description": "INTELIJ, GIT, JENKINS"
        },
        {
          "iconPack": "fas",
          "icon": "tasks",
          "description": "AGILE SCRUM"
        }
      ],
      "tasks": [
        "Collecte, analyse, et consolidation de données omnichannel en temps réel",
        "Réalisation de tableaux de bord dédiés à la collecte de statistiques",
        "Intégration des librairies tierces : Highcharts, jsPlumb, D3.js, heatmap.js",
        "Prise en charge de la partie UI/UX et du Design System de l’application"
      ]
    },
    {
      "title": "Ingénieur Etudes et Développement - SII",
      "company": "SOFTWAY MEDICAL | Service dqzd - France",
      "year": "Juin 2013 - Novembre 2014",
      "description": "Internationalisation d'un ERP médical",
      "environments": [
        {
          "iconPack": "fab",
          "icon": "angular",
          "description": "REST, JSON, RTC"
        },
        {
          "iconPack": "fas",
          "icon": "leaf",
          "description": "JAVA, JPA, TOMCAT, ORACLE, JUNIT, JSP, STRUTS"
        },
        {
          "iconPack": "fab",
          "icon": "github",
          "description": "ECLIPSE, GIT, JENKINS"
        },
        {
          "iconPack": "fas",
          "icon": "tasks",
          "description": "AGILE SCRUM"
        }
      ],
      "tasks": [
        "Recueil et analyse du besoin, recherche de solutions",
        "Étude des problématiques d’architecture liées à la localisation des données",
        "Mise en place de mécanismes d’internationalisation transverses",
        "TDD"
      ]
    },
    {
      "title": "Développeur Fullstack - SII",
      "company": "GRAND PORT MARITIME DE MARSEILLE | Service dqzd - France",
      "year": "Juin 2012 - Novembre 2013",
      "description": "Conception d'un système de paramétrage et de contôle des escales maritimes",
      "environments": [
        {
          "iconPack": "fab",
          "icon": "angular",
          "description": "CSS"
        },
        {
          "iconPack": "fas",
          "icon": "leaf",
          "description": "JAVA, GWT, JPA, JBOSS, ORACLE"
        },
        {
          "iconPack": "fab",
          "icon": "github",
          "description": "ECLIPSE, GIT, JENKINS"
        },
        {
          "iconPack": "fas",
          "icon": "tasks",
          "description": "AGILE SCRUM, UML"
        }
      ],
      "tasks": [
        "Conception et développement d'un socle technique",
        "Réalisation d'une bibliothèque de composants basé sur le framework GWT",
        "Contrôle qualité et intégration continue"
      ]
    },
    {
      "title": "Tech leader / Développeur Fullstack - SII",
      "company": "FRANCE TELECOM | Service dqzd - France",
      "year": "Juin 2010 - Novembre 2012",
      "description": "Conception d’une application de prévention des surconsommations téléphoniques",
      "environments": [
        {
          "iconPack": "fab",
          "icon": "angular",
          "description": "HTML"
        },
        {
          "iconPack": "fas",
          "icon": "leaf",
          "description": "JAVA, HUDSON, WICKET, JPA, MYSQL, SPRING BATCH, JONAS, JUNIT, JSP, STRUTS"
        },
        {
          "iconPack": "fab",
          "icon": "github",
          "description": "ECLIPSE, SVN, JENKINS, QUALITY CENTER"
        },
        {
          "iconPack": "fas",
          "icon": "tasks",
          "description": "UML"
        }
      ],
      "tasks": [
        "Étude de faisabilité",
        "Définition de l’architecture logicielle du projet",
        "Conception, développement et maintenance de l’application",
        "Suivi de production"
      ]
    },
    {
      "title": "Ingénieur Etudes et Développement - Capgemini",
      "company": "AMADEUS | Sofia-Antipolis - Nice - France",
      "year": "Juin 2009 - Novembre 2010",
      "description": "Maintenance corrective et évolutive d’un outil de réservation global pour le marché des voyages d’affaires : Amadeus e-Travel Management",
      "environments": [
        {
          "iconPack": "fab",
          "icon": "angular",
          "description": "JAVASCRIPT, HTML"
        },
        {
          "iconPack": "fas",
          "icon": "leaf",
          "description": "JAVA, JSP, WEBLOGIC SERVER, CLEARCASE, SQL, QUERY ANALYZER, SPRING WEB FLOW"
        },
        {
          "iconPack": "fab",
          "icon": "github",
          "description": "ECLIPSE, QUALITY CENTER"
        },
        {
          "iconPack": "fas",
          "icon": "tasks",
          "description": "AGILE SCRUM"
        }
      ],
      "tasks": [
        "Intégration d’un contexte international",
        "Validation logicielle, exécution de campagnes de tests",
        "Suivi des bugs et anomalies via WIN@proach"
      ]
    },
    {
      "title": "Ingénieur Etudes et Développement - Capgemini",
      "company": "ASSISTANCE PUBLIQUE | Hôpitaux de Marseille - Marseille - France",
      "year": "Juin 2007 - Novembre 2009",
      "description": "Conception, développement et maintenance d'applications Web de gestion des ressources humaines",
      "environments": [
        {
          "iconPack": "fab",
          "icon": "angular",
          "description": "HTML, AJAX, EXTJS"
        },
        {
          "iconPack": "fas",
          "icon": "leaf",
          "description": "JAVA, GWT, JPA, HIBERNATE, TOMCAT, ORACLE, JUNIT, JSP, STRUTS, SPRING MVC"
        },
        {
          "iconPack": "fab",
          "icon": "github",
          "description": "ECLIPSE, SVN"
        },
        {
          "iconPack": "fas",
          "icon": "tasks",
          "description": "AGILE SCRUM"
        }
      ],
      "tasks": [
        "Conception et développement d’une application de suivi de carrière du personnel hospitalier",
        "Implémentation d’interfaces riche à l'aide de Ext-JS et GWT",
        "Création de modules d'import / export de données au format pdf",
        "Élaboration de tests unitaires"
      ]
    }
  ],
  "educations": [
    {
      "title": "DIPLOME D’INGENIEUR EN INFORMATIQUE, GENIE LOGICIEL",
      "studies": "Ecole Supérieure d’Ingénieurs de Luminy - Marseille - France",
      "year": "2003 - 2006"
    },
    {
      "title": "CPGE, MATHEMATIQUES ET PHYSIQUE",
      "studies": "Lycée Clémenceau - Reims - France",
      "year": "2001 - 2003"
    }
  ],
  "interests": [
    {
      "title": "Plongée N2",
      "icon": "fa-water",
      "iconPack": "fas"
    },
    {
      "title": "Photo",
      "icon": "fa-camera",
      "iconPack": "fas"
    },
    {
      "title": "Movies/Series",
      "icon": "fa-film",
      "iconPack": "fas"
    },
    {
      "title": "Padel",
      "icon": "fa-table-tennis-paddle-ball",
      "iconPack": "fas"
    },
    {
      "title": "Program",
      "icon": "fa-code",
      "iconPack": "fas"
    },
    {
      "title": "Running",
      "icon": "fa-person-running",
      "iconPack": "fas"
    }
  ]
}
